{
  "list":[
    {
      "src":"../images/test.jpg",
      "name":"绿之叶公益2016年秋季支教老师招募",
      "address":"北京市-朝阳区",
      "user":{"type":11,"nickname":"康县义工联合会"},
      "resource":"一瓶水,一个面包",
      "statu":0
    },
    {
      "src":"../images/test.jpg",
      "name":"绿之叶公益2016年秋季支教老师招募",
      "address":"北京市-海淀区",
      "user":{"type":21,"nickname":"康县义工联合会"},
      "resource":"一瓶水,一个面包",
      "statu":1
    },
    {
      "src":"../images/test.jpg",
      "name":"绿之叶公益2016年秋季支教老师招募",
      "address":"北京市-朝阳区",
      "user":{"type":11,"nickname":"康县义工联合会"},
      "resource":"一瓶水,一个面包",
      "statu":0
    },
    {
      "src":"../images/test.jpg",
      "name":"绿之叶公益2016年秋季支教老师招募",
      "address":"北京市-朝阳区",
      "user":{"type":11,"nickname":"康县义工联合会"},
      "resource":"一瓶水,一个面包,一个手机",
      "statu":1
    },
    {
      "src":"../images/test.jpg",
      "name":"绿之叶公益2016年秋季支教老师招募",
      "address":"北京市-怀柔区",
      "user":{"type":21,"nickname":"康县义工联合会"},
      "resource":"一瓶水,一个面包",
      "statu":0
    },
    {
      "src":"../images/test.jpg",
      "name":"绿之叶公益2016年秋季支教老师招募",
      "address":"北京市-丰台区",
      "user":{"type":11,"nickname":"康县义工联合会"},
      "resource":"一瓶水,一个面包",
      "statu":0
    }

  ],
  "total":6
}